hyp3_sbas/__init__.py
hyp3_sbas/_version.py
hyp3_sbas/classes.py
hyp3_sbas/setup.py
hyp3_sbas-0.1.0.dist-info/LICENSE.txt
hyp3_sbas-0.1.0.dist-info/METADATA
hyp3_sbas-0.1.0.dist-info/WHEEL
hyp3_sbas-0.1.0.dist-info/top_level.txt
hyp3_sbas-0.1.0.dist-info/RECORD
