Metadata-Version: 2.1
Name: hyp3_sbas
Version: 0.1.0
Summary: HyP3 product generation for SBAS processing
Author-email: Adolfo Molada Tebar <a.molada.tebar@gmail.com>
Classifier: Programming Language :: Python :: 3.8
Classifier: License :: OSI Approved :: GNU General Public License v3 (GPLv3)
Classifier: Operating System :: OS Independent
Requires-Python: >=3.8
License-File: LICENSE.txt
